dns_over_https.py
dns_over_https-0.0.2.dist-info/DESCRIPTION.rst
dns_over_https-0.0.2.dist-info/METADATA
dns_over_https-0.0.2.dist-info/RECORD
dns_over_https-0.0.2.dist-info/WHEEL
dns_over_https-0.0.2.dist-info/metadata.json
dns_over_https-0.0.2.dist-info/top_level.txt
