Metadata-Version: 2.0
Name: dns-over-https
Version: 0.0.2
Summary: Python client for Google's Public DNS-over-HTTPS service
Home-page: https://www.github.com/wglodek/dns-over-https
Author: William Glodek
Author-email: wglodek@breakpoint-labs.com
License: MIT
Download-URL: https://www.github.com/wglodek/dns-over-https/dns_over_https/tarball/0.0.1
Keywords: google dns https
Platform: UNKNOWN
Classifier: Programming Language :: Python
Classifier: Programming Language :: Python :: 2.6
Classifier: Programming Language :: Python :: 2.7
Classifier: Programming Language :: Python :: 3.3
Classifier: Programming Language :: Python :: 3.4
Classifier: Programming Language :: Python :: 3.5
Classifier: License :: OSI Approved :: MIT License
Classifier: Development Status :: 3 - Alpha
Requires-Dist: requests
